omc4py/__init__.py
omc4py/algorithm.py
omc4py/exception.py
omc4py/interactive.py
omc4py/modelica.py
omc4py/openmodelica.py
omc4py/parser.py
omc4py/protocol.py
omc4py/py.typed
omc4py/session.py
omc4py/v_1_13/OpenModelica/Internal/Architecture/__init__.py
omc4py/v_1_13/OpenModelica/Internal/__init__.py
omc4py/v_1_13/OpenModelica/Scripting/Experimental/__init__.py
omc4py/v_1_13/OpenModelica/Scripting/Internal/Time/__init__.py
omc4py/v_1_13/OpenModelica/Scripting/Internal/__init__.py
omc4py/v_1_13/OpenModelica/Scripting/__init__.py
omc4py/v_1_13/OpenModelica/UsersGuide/ReleaseNotes/__init__.py
omc4py/v_1_13/OpenModelica/UsersGuide/__init__.py
omc4py/v_1_13/OpenModelica/__init__.py
omc4py/v_1_13/__init__.py
omc4py/v_1_14/OpenModelica/AutoCompletion/Annotations/__init__.py
omc4py/v_1_14/OpenModelica/AutoCompletion/__init__.py
omc4py/v_1_14/OpenModelica/Internal/Architecture/__init__.py
omc4py/v_1_14/OpenModelica/Internal/__init__.py
omc4py/v_1_14/OpenModelica/Scripting/Experimental/__init__.py
omc4py/v_1_14/OpenModelica/Scripting/Internal/Time/__init__.py
omc4py/v_1_14/OpenModelica/Scripting/Internal/__init__.py
omc4py/v_1_14/OpenModelica/Scripting/__init__.py
omc4py/v_1_14/OpenModelica/UsersGuide/ReleaseNotes/__init__.py
omc4py/v_1_14/OpenModelica/UsersGuide/__init__.py
omc4py/v_1_14/OpenModelica/__init__.py
omc4py/v_1_14/__init__.py
omc4py/v_1_15/OpenModelica/AutoCompletion/Annotations/__init__.py
omc4py/v_1_15/OpenModelica/AutoCompletion/__init__.py
omc4py/v_1_15/OpenModelica/Internal/Architecture/__init__.py
omc4py/v_1_15/OpenModelica/Internal/__init__.py
omc4py/v_1_15/OpenModelica/Scripting/Experimental/__init__.py
omc4py/v_1_15/OpenModelica/Scripting/Internal/Time/__init__.py
omc4py/v_1_15/OpenModelica/Scripting/Internal/__init__.py
omc4py/v_1_15/OpenModelica/Scripting/__init__.py
omc4py/v_1_15/OpenModelica/UsersGuide/ReleaseNotes/__init__.py
omc4py/v_1_15/OpenModelica/UsersGuide/__init__.py
omc4py/v_1_15/OpenModelica/__init__.py
omc4py/v_1_15/__init__.py
openmodelicacompiler-0.3.3.dist-info/COPYING
openmodelicacompiler-0.3.3.dist-info/METADATA
openmodelicacompiler-0.3.3.dist-info/WHEEL
openmodelicacompiler-0.3.3.dist-info/RECORD
