Metadata-Version: 2.1
Name: OpenModelicaCompiler
Version: 0.3.3
Summary: OpenModelica compiler (omc) interface for Python
Home-page: https://github.com/ijknabla/OpenModelicaCompilerForPython
License: GPL-3.0, OSMC-PL 1.2 (user's choice)
Author: ijknabla
Author-email: ijknabla@gmail.com
Requires-Python: >=3.8,<4.0
Classifier: Development Status :: 5 - Production/Stable
Classifier: License :: Other/Proprietary License
Classifier: Programming Language :: Python :: 3
Classifier: Programming Language :: Python :: 3.8
Classifier: Programming Language :: Python :: 3.9
Classifier: Programming Language :: Python :: 3.10
Classifier: Programming Language :: Python :: 3.11
Classifier: Programming Language :: Python :: 3.12
Classifier: Programming Language :: Python :: 3 :: Only
Classifier: Topic :: Scientific/Engineering :: Mathematics
Classifier: Topic :: Scientific/Engineering :: Physics
Classifier: Topic :: Software Development :: User Interfaces
Requires-Dist: arpeggio (>=1.6)
Requires-Dist: exceptiongroup (>=1.0)
Requires-Dist: modelicalang (>=0.1.0a2,<0.2.0)
Requires-Dist: pyzmq (>=17.0.0)
Requires-Dist: tornado (>=6.1) ; sys_platform == "win32"
Requires-Dist: typing-extensions (>=3.7.4)
Project-URL: Repository, https://github.com/ijknabla/OpenModelicaCompilerForPython
